README.txt
setup.py
pydigmips/__init__.py
pydigmips/__main__.py
pydigmips/assembly_analysis.py
pydigmips/compatibility.py
pydigmips/emulator.py
pydigmips/instructions.py
pydigmips/loaders.py
pydigmips/state.py
pydigmips.egg-info/PKG-INFO
pydigmips.egg-info/SOURCES.txt
pydigmips.egg-info/dependency_links.txt
pydigmips.egg-info/top_level.txt