Metadata-Version: 1.1
Name: pydigmips
Version: 0.2
Summary: DigMIPS interpreter.
Home-page: https://github.com/ProjetPP/pydigmips
Author: Valentin Lorentz
Author-email: valentin.lorentz+ppp@ens-lyon.org
License: MIT
Platform: UNKNOWN
Classifier: Environment :: Console
Classifier: Development Status :: 3 - Alpha
Classifier: Intended Audience :: Education
Classifier: Intended Audience :: Science/Research
Classifier: License :: OSI Approved :: MIT License
Classifier: Operating System :: OS Independent
Classifier: Programming Language :: Python :: 3
Classifier: Programming Language :: Python :: 3.2
Classifier: Programming Language :: Python :: 3.3
Classifier: Programming Language :: Python :: 3.4
Classifier: Topic :: Software Development :: Assemblers
Classifier: Topic :: Software Development :: Code Generators
Classifier: Topic :: Software Development :: Compilers
